{
 "collisions":[

{"x_collision":632,"y_collision":184,"date":"01:00:29 | 29-05-2023"},
{"x_collision":116,"y_collision":35,"date":"01:00:30 | 29-05-2023"},
{"x_collision":1207,"y_collision":314,"date":"01:00:30 | 29-05-2023"},
{"x_collision":281,"y_collision":347,"date":"01:00:30 | 29-05-2023"},
{"x_collision":626,"y_collision":664,"date":"01:00:30 | 29-05-2023"},
{"x_collision":680,"y_collision":653,"date":"01:00:31 | 29-05-2023"},
{"x_collision":686,"y_collision":661,"date":"01:00:31 | 29-05-2023"},
{"x_collision":879,"y_collision":476,"date":"01:00:31 | 29-05-2023"},
{"x_collision":712,"y_collision":686,"date":"01:00:31 | 29-05-2023"},
{"x_collision":689,"y_collision":684,"date":"01:00:31 | 29-05-2023"},
{"x_collision":713,"y_collision":687,"date":"01:00:31 | 29-05-2023"},
{"x_collision":521,"y_collision":154,"date":"01:00:32 | 29-05-2023"},
{"x_collision":865,"y_collision":590,"date":"01:00:32 | 29-05-2023"},
{"x_collision":177,"y_collision":118,"date":"01:00:32 | 29-05-2023"},
{"x_collision":24,"y_collision":75,"date":"01:00:32 | 29-05-2023"},
{"x_collision":630,"y_collision":602,"date":"01:00:32 | 29-05-2023"},
{"x_collision":946,"y_collision":558,"date":"01:00:33 | 29-05-2023"},
{"x_collision":1348,"y_collision":325,"date":"01:00:33 | 29-05-2023"},
{"x_collision":670,"y_collision":209,"date":"01:00:33 | 29-05-2023"},
{"x_collision":1301,"y_collision":469,"date":"01:00:34 | 29-05-2023"},
{"x_collision":1315,"y_collision":419,"date":"01:00:34 | 29-05-2023"},
{"x_collision":936,"y_collision":396,"date":"01:00:34 | 29-05-2023"},
{"x_collision":1372,"y_collision":550,"date":"01:00:34 | 29-05-2023"},
{"x_collision":1141,"y_collision":288,"date":"01:00:34 | 29-05-2023"},
{"x_collision":1280,"y_collision":442,"date":"01:00:34 | 29-05-2023"},
{"x_collision":1052,"y_collision":290,"date":"01:00:34 | 29-05-2023"},
{"x_collision":1250,"y_collision":455,"date":"01:00:34 | 29-05-2023"},
{"x_collision":1065,"y_collision":557,"date":"01:00:35 | 29-05-2023"},
{"x_collision":569,"y_collision":170,"date":"01:00:35 | 29-05-2023"},
{"x_collision":423,"y_collision":66,"date":"01:00:35 | 29-05-2023"},
{"x_collision":846,"y_collision":443,"date":"01:00:36 | 29-05-2023"},
{"x_collision":828,"y_collision":466,"date":"01:00:36 | 29-05-2023"},
{"x_collision":959,"y_collision":401,"date":"01:00:36 | 29-05-2023"},
{"x_collision":676,"y_collision":558,"date":"01:00:36 | 29-05-2023"},
{"x_collision":377,"y_collision":94,"date":"01:00:36 | 29-05-2023"},
{"x_collision":1105,"y_collision":496,"date":"01:00:37 | 29-05-2023"},
{"x_collision":1123,"y_collision":320,"date":"01:00:37 | 29-05-2023"},
{"x_collision":1122,"y_collision":520,"date":"01:00:37 | 29-05-2023"},
{"x_collision":1325,"y_collision":116,"date":"01:00:38 | 29-05-2023"},
{"x_collision":986,"y_collision":335,"date":"01:00:38 | 29-05-2023"},
{"x_collision":1166,"y_collision":121,"date":"01:00:38 | 29-05-2023"},
{"x_collision":1010,"y_collision":369,"date":"01:00:38 | 29-05-2023"},
{"x_collision":976,"y_collision":373,"date":"01:00:38 | 29-05-2023"},
{"x_collision":1229,"y_collision":39,"date":"01:00:38 | 29-05-2023"},
{"x_collision":1182,"y_collision":573,"date":"01:00:38 | 29-05-2023"},
{"x_collision":1255,"y_collision":28,"date":"01:00:38 | 29-05-2023"},
{"x_collision":1222,"y_collision":134,"date":"01:00:38 | 29-05-2023"},
{"x_collision":720,"y_collision":387,"date":"01:00:38 | 29-05-2023"},
{"x_collision":1242,"y_collision":239,"date":"01:00:39 | 29-05-2023"},
{"x_collision":606,"y_collision":394,"date":"01:00:39 | 29-05-2023"},
{"x_collision":1123,"y_collision":137,"date":"01:00:39 | 29-05-2023"},
{"x_collision":1327,"y_collision":382,"date":"01:00:39 | 29-05-2023"},
{"x_collision":60,"y_collision":243,"date":"01:00:39 | 29-05-2023"},
{"x_collision":1056,"y_collision":314,"date":"01:00:39 | 29-05-2023"},
{"x_collision":16,"y_collision":505,"date":"01:00:40 | 29-05-2023"},
{"x_collision":1280,"y_collision":37,"date":"01:00:40 | 29-05-2023"},
{"x_collision":1120,"y_collision":207,"date":"01:00:40 | 29-05-2023"},
{"x_collision":834,"y_collision":458,"date":"01:00:40 | 29-05-2023"},
{"x_collision":1293,"y_collision":540,"date":"01:00:40 | 29-05-2023"},
{"x_collision":104,"y_collision":64,"date":"01:00:40 | 29-05-2023"},
{"x_collision":576,"y_collision":157,"date":"01:00:40 | 29-05-2023"},
{"x_collision":1345,"y_collision":129,"date":"01:00:40 | 29-05-2023"},
{"x_collision":1056,"y_collision":678,"date":"01:00:41 | 29-05-2023"},
{"x_collision":972,"y_collision":22,"date":"01:00:41 | 29-05-2023"},
{"x_collision":1066,"y_collision":680,"date":"01:00:41 | 29-05-2023"},
{"x_collision":1285,"y_collision":368,"date":"01:00:41 | 29-05-2023"},
{"x_collision":294,"y_collision":670,"date":"01:00:41 | 29-05-2023"},
{"x_collision":323,"y_collision":668,"date":"01:00:41 | 29-05-2023"},
{"x_collision":947,"y_collision":519,"date":"01:00:41 | 29-05-2023"},
{"x_collision":1320,"y_collision":360,"date":"01:00:42 | 29-05-2023"},
{"x_collision":1297,"y_collision":502,"date":"01:00:42 | 29-05-2023"},
{"x_collision":121,"y_collision":567,"date":"01:00:42 | 29-05-2023"},
{"x_collision":866,"y_collision":613,"date":"01:00:42 | 29-05-2023"},
{"x_collision":475,"y_collision":327,"date":"01:00:42 | 29-05-2023"},
{"x_collision":859,"y_collision":74,"date":"01:00:43 | 29-05-2023"},
{"x_collision":1068,"y_collision":614,"date":"01:00:43 | 29-05-2023"},
{"x_collision":909,"y_collision":234,"date":"01:00:44 | 29-05-2023"},
{"x_collision":1006,"y_collision":212,"date":"01:00:44 | 29-05-2023"},
{"x_collision":640,"y_collision":120,"date":"01:00:45 | 29-05-2023"},
{"x_collision":569,"y_collision":403,"date":"01:00:45 | 29-05-2023"},
{"x_collision":901,"y_collision":172,"date":"01:00:45 | 29-05-2023"},
{"x_collision":225,"y_collision":279,"date":"01:00:46 | 29-05-2023"},
{"x_collision":244,"y_collision":361,"date":"01:00:46 | 29-05-2023"},
{"x_collision":751,"y_collision":100,"date":"01:00:46 | 29-05-2023"},
{"x_collision":63,"y_collision":219,"date":"01:00:46 | 29-05-2023"},
{"x_collision":221,"y_collision":367,"date":"01:00:46 | 29-05-2023"},
{"x_collision":1277,"y_collision":626,"date":"01:00:46 | 29-05-2023"},
{"x_collision":541,"y_collision":609,"date":"01:00:46 | 29-05-2023"},
{"x_collision":177,"y_collision":153,"date":"01:00:47 | 29-05-2023"},
{"x_collision":760,"y_collision":200,"date":"01:00:47 | 29-05-2023"},
{"x_collision":252,"y_collision":350,"date":"01:00:47 | 29-05-2023"}
]}